mltemp/__init__.py
mltemp/mltemplate.py
mltemp-0.2.6.dist-info/METADATA
mltemp-0.2.6.dist-info/WHEEL
mltemp-0.2.6.dist-info/entry_points.txt
mltemp-0.2.6.dist-info/top_level.txt
mltemp-0.2.6.dist-info/RECORD
