Metadata-Version: 2.1
Name: mltemp
Version: 0.2.6
